{
  "project_info": {
    "project_number": "851062430855",
    "project_id": "hotelamangement",
    "storage_bucket": "hotelamangement.appspot.com"
  },
  "client": [
    {
      "client_info": {
        "mobilesdk_app_id": "1:851062430855:android:ab6b064333f7fbf8286c22",
        "android_client_info": {
          "package_name": "com.example.hotelmanagement"
        }
      },
      "oauth_client": [],
      "api_key": [
        {
          "current_key": "AIzaSyDhLhxVz5yB1E3nt_pTpnfIiWQONUbg5dM"
        }
      ],
      "services": {
        "appinvite_service": {
          "other_platform_oauth_client": []
        }
      }
    }
  ],
  "configuration_version": "1"
}